{
    "className": "org.joget.apps.userview.model.Userview",
    "categories": [
        {
            "className": "org.joget.apps.userview.model.UserviewCategory",
            "menus": [{
                "className": "org.joget.apps.userview.lib.HtmlPage",
                "properties": {
                    "userviewCacheDuration": "",
                    "userviewCacheScope": "",
                    "id": "e8b2dfa1-9caf-4e30-8431-f8600944d8d5",
                    "label": "Welcome",
                    "enableOffline": "",
                    "customId": "welcome",
                    "content": "<div class=\"ui-welcome\">\n<h1>Apps and Workflow Made Simple<\/h1>\n<p>&nbsp;<\/p>\n<div class=\"icon\" style=\"margin-right: 20px; margin-bottom: 20px; float: left; clear: left;\"><img src=\"/jw/images/icon_idea.png\" alt=\"Build apps\" width=\"120\" height=\"85\"><\/div>\n<div class=\"message\">\n<h3>Build apps, not just processes!<\/h3>\n<p>Create full-fledged apps with support for data records management.<\/p>\n<\/div>\n<p>&nbsp;<\/p>\n<div class=\"icon\" style=\"margin-right: 20px; margin-bottom: 20px; float: left; clear: left;\"><img src=\"/jw/images/icon_rocket.png\" alt=\"Increased efficiency\" width=\"120\" height=\"85\"><\/div>\n<div class=\"message\">\n<h3>Increased Efficiency and Productivity<\/h3>\n<p>Faster and more consistent completion of manual processes, and with minimal errors.<\/p>\n<\/div>\n<p>&nbsp;<\/p>\n<div class=\"icon\" style=\"margin-right: 20px; margin-bottom: 20px; float: left; clear: left;\"><img src=\"/jw/images/icon_cost.png\" alt=\"Lowered cost\" width=\"120\" height=\"85\"><\/div>\n<div class=\"message\">\n<h3>Lowered Cost<\/h3>\n<p>Employees can be guided through complex procedures, hence reducing the cost of training.<\/p>\n<\/div>\n<\/div>"
                }
            }],
            "properties": {
                "id": "category-EE74E4F4426241BD9BC3BC73B1D24AC7",
                "label": "<i class='fa fa-home'><\/i> Home"
            }
        },
        {
            "className": "org.joget.apps.userview.model.UserviewCategory",
            "menus": [
                {
                    "className": "org.joget.apps.userview.lib.DataListMenu",
                    "properties": {
                        "cacheAllLinks": "",
                        "customHeader": "",
                        "keyName": "",
                        "customFooter": "",
                        "label": "History Mail Client",
                        "enableOffline": "",
                        "customId": "history_mail_client",
                        "buttonPosition": "bottomLeft",
                        "datalistId": "list_history_client",
                        "checkboxPosition": "left",
                        "selectionType": "multiple",
                        "userviewCacheDuration": "20",
                        "cacheListAction": "",
                        "userviewCacheScope": "",
                        "rowCount": "",
                        "id": "D6AB75BB1172469223467985B3B80E30"
                    }
                },
                {
                    "className": "org.joget.apps.userview.lib.DataListMenu",
                    "properties": {
                        "cacheAllLinks": "",
                        "customHeader": "",
                        "keyName": "",
                        "customFooter": "",
                        "label": "History Mail Government",
                        "enableOffline": "",
                        "customId": "history_mail_government",
                        "buttonPosition": "bothLeft",
                        "datalistId": "history_mail_goverment",
                        "checkboxPosition": "left",
                        "selectionType": "multiple",
                        "userviewCacheDuration": "20",
                        "cacheListAction": "",
                        "userviewCacheScope": "",
                        "rowCount": "",
                        "id": "581E7615008F4339586C37D04F0F1A0A"
                    }
                }
            ],
            "properties": {
                "hide": "",
                "permission": {
                    "className": "",
                    "properties": {}
                },
                "comment": "",
                "label": "Incoming Mail",
                "id": "category-88F79F54919C425DBB0C7327E59AFE4C"
            }
        },
        {
            "className": "org.joget.apps.userview.model.UserviewCategory",
            "menus": [{
                "className": "org.joget.apps.userview.lib.FormMenu",
                "properties": {
                    "loadDataWithKey": "",
                    "redirectUrlOnCancel": "",
                    "actionOnCancel": "",
                    "redirectTargetOnCancel": "top",
                    "customFooter": "",
                    "paramName": "",
                    "enableOffline": "",
                    "afterSavedReloadTarget": "true",
                    "customId": "form_reply_client",
                    "showInPopupDialog": "",
                    "readonly": "",
                    "cancelButtonLabel": "",
                    "actionAfterSaved": "",
                    "id": "FE66BAF15A8A45A5AAC6CD917630EBCF",
                    "redirectUrlAfterComplete": "",
                    "fieldPassover": "",
                    "formId": "reply_mail_client",
                    "customHeader": "",
                    "fieldPassoverMethod": "append",
                    "redirectTargetOnComplete": "",
                    "keyName": "",
                    "label": "Form reply client",
                    "userviewCacheDuration": "20",
                    "messageShowAfterComplete": "",
                    "submitButtonLabel": "",
                    "userviewCacheScope": "",
                    "readonlyLabel": "true"
                }
            }],
            "properties": {
                "hide": "",
                "permission": {
                    "className": "",
                    "properties": {}
                },
                "comment": "",
                "label": "Form Reply",
                "id": "category-AD7257A4157F4E8E0168A705DC6C63C5"
            }
        }
    ],
    "properties": {
        "logoutText": "Logout",
        "welcomeMessage": "#date.EEE, d MMM yyyy#",
        "name": "UI Danny",
        "description": "",
        "footerMessage": "Powered by Joget",
        "id": "uiDanny"
    },
    "setting": {"properties": {
        "userviewDescription": "",
        "userviewId": "uiDanny",
        "theme": {
            "className": "org.joget.apps.userview.lib.AjaxUniversalTheme",
            "properties": {
                "mobileViewDisabled": "",
                "userImage": "no",
                "dx8colorScheme": "#e9e9e9;#FFFFFF;#AECAC7;#2C6562;#1976d2;#004ba0",
                "mobileCacheEnabled": ""
            }
        },
        "permission": {
            "className": "org.joget.apps.userview.lib.LoggedInUserPermission",
            "properties": {}
        },
        "userviewName": "UI Danny"
    }}
}